e621_content_collector/__init__.py
e621_content_collector/__main__.py
e621_content_collector/cli.py
e621_content_collector/downloader/__init__.py
e621_content_collector/downloader/download.py
e621_content_collector/downloader/set_up_database_structure.sql
e621_content_collector-0.5.0.dist-info/METADATA
e621_content_collector-0.5.0.dist-info/WHEEL
e621_content_collector-0.5.0.dist-info/entry_points.txt
e621_content_collector-0.5.0.dist-info/licenses/LICENSE
e621_content_collector-0.5.0.dist-info/RECORD
