Metadata-Version: 2.4
Name: e621_content_collector
Version: 0.5.0
Summary: A simple tool for gathering content from e621 for local use.
Project-URL: Homepage, https://github.com/darkroastcreative/e621-content-collector
Project-URL: Repository, https://github.com/darkroastcreative/e621-content-collector
Project-URL: Issues, https://github.com/darkroastcreative/e621-content-collector/issues
Author-email: David Urso <david@darkroastcreative.co>
Maintainer-email: David Urso <david@darkroastcreative.co>
License-Expression: AGPL-3.0-only
License-File: LICENSE
Keywords: downloader,e621,e621-downloader,furry
Classifier: Development Status :: 3 - Alpha
Classifier: License :: OSI Approved :: GNU Affero General Public License v3
Classifier: Operating System :: OS Independent
Classifier: Programming Language :: Python :: 3
Classifier: Programming Language :: Python :: 3.12
Requires-Python: >=3.12
Requires-Dist: requests
Requires-Dist: typer
